{
    "Building Hours": {
        "Monday": "6:00 AM - 8:00 PM",
        "Tuesday": "6:00 AM - 8:00 PM",
        "Wednesday": "6:00 AM - 8:00 PM",
        "Thursday": "6:00 AM - 8:00 PM",
        "Friday": "6:00 AM - 8:00 PM",
        "Saturday": "9:00 AM - 6:00 PM",
        "Sunday": "1:00 PM - 8:00 PM"
    },
    "Climbing Wall Hours": {
        "Monday": "CLOSED",
        "Tuesday": "2:00 PM - 5:00 PM",
        "Wednesday": "2:00 PM - 5:00 PM",
        "Thursday": "2:00 PM - 5:00 PM",
        "Friday": "2:00 PM - 5:00 PM",
        "Saturday": "CLOSED",
        "Sunday": "CLOSED"
    },
    "Pool and Sauna Hours": {
        "Monday": "6:00 AM - 11:00 AM / 3:00 PM - 6:00 PM",
        "Tuesday": "6:00 AM - 11:00 AM / 3:00 PM - 6:00 PM",
        "Wednesday": "6:00 AM - 11:00 AM / 3:00 PM - 6:00 PM",
        "Thursday": "6:00 AM - 11:00 AM / 3:00 PM - 6:00 PM",
        "Friday": "6:00 AM - 11:00 AM / 3:00 PM - 6:00 PM",
        "Saturday": "CLOSED",
        "Sunday": "CLOSED"
    },
    "Updated Time": "Updated: 7/8/2024",
    "Current Time": "2024-07-13 16:47:34"
}